[
  {
    "outputFileName": "Content/bundle.css",
    "inputFiles": [
      "Frontend/Css/reset.css",

      "Frontend/Css/ie10-viewport-bug-workaround.css",

      "Frontend/Css/style.css"

    ],
    "minify": {
      "enabled": true,
      "commentMode": "none"
    }
  },
  {
    "outputFileName": "Scripts/app.js",
    "inputFiles": [

      "Frontend/Js/Modules/jquery.scrollex.min.js",
      "Frontend/Js/Modules/jquery.scrolly.min.js",
      "Frontend/Js/Modules/skel.min.js",
      "Frontend/Js/Modules/skel-viewport.js",
      "Frontend/Js/Modules/skel-layout.min.js",
      "Frontend/Js/Modules/init.js"

    ]
  },
  {
    "outputFileName": "Content/bundle.min.css",
    "inputFiles": [
      "Content/bundle.css"
    ]
  },
  {
    "outputFileName": "Scripts/app.min.js",
    "inputFiles": [
      "Scripts/app.js"
    ]
  }
]
